ww_normalize_loudness/run.bat
ww_normalize_loudness/run.sh
ww_normalize_loudness/src/ww_normalize_loudness.proto
ww_normalize_loudness/src/ww_normalize_loudness_cli.py
ww_normalize_loudness/src/ww_normalize_loudness_core.py
ww_normalize_loudness/src/ww_normalize_loudness_output.py
ww_normalize_loudness/src/ww_normalize_loudness_schema.json
ww_normalize_loudness/tool/control.py
ww_normalize_loudness/tool/help.html
ww_normalize_loudness/tool/help.md
ww_normalize_loudness/tool/tool.bat
ww_normalize_loudness/tool/tool.json
ww_normalize_loudness/tool/tool.png
ww_normalize_loudness/tool/tool.py
ww_normalize_loudness/tool/tool.sh
ww_normalize_loudness/wwise/ww_normalize_loudness.mac.wca.json
ww_normalize_loudness-2.0.5.dist-info/METADATA
ww_normalize_loudness-2.0.5.dist-info/WHEEL
ww_normalize_loudness-2.0.5.dist-info/entry_points.txt
ww_normalize_loudness-2.0.5.dist-info/RECORD
